fps_auth/__init__.py
fps_auth/backends.py
fps_auth/config.py
fps_auth/db.py
fps_auth/main.py
fps_auth/models.py
fps_auth/py.typed
fps_auth/routes.py
fps_auth-0.9.6.dist-info/licenses/COPYING.md
fps_auth-0.9.6.dist-info/WHEEL
fps_auth-0.9.6.dist-info/entry_points.txt
fps_auth-0.9.6.dist-info/METADATA
fps_auth-0.9.6.dist-info/RECORD
